mfd_libibverbs_utils/__init__.py
mfd_libibverbs_utils/exceptions.py
mfd_libibverbs_utils/ibv_devices.py
mfd_libibverbs_utils/ibv_devinfo.py
mfd_libibverbs_utils/libibverbs_tool.py
mfd_libibverbs_utils-1.7.0.dist-info/licenses/AUTHORS.md
mfd_libibverbs_utils-1.7.0.dist-info/licenses/LICENSE.md
mfd_libibverbs_utils-1.7.0.dist-info/METADATA
mfd_libibverbs_utils-1.7.0.dist-info/WHEEL
mfd_libibverbs_utils-1.7.0.dist-info/top_level.txt
mfd_libibverbs_utils-1.7.0.dist-info/RECORD
