Metadata-Version: 2.4
Name: mfd-libibverbs-utils
Version: 1.7.0
Summary: Module for running libibverbs tools for getting information about Remote Direct Memory Access (RDMA) devices installed in system
Project-URL: Homepage, https://github.com/intel/mfd
Project-URL: Repository, https://github.com/intel/mfd-libibverbs-utils
Project-URL: Issues, https://github.com/intel/mfd-libibverbs-utils/issues
Project-URL: Changelog, https://github.com/intel/mfd-libibverbs-utils/blob/main/CHANGELOG.md
Requires-Python: <3.14,>=3.10
License-File: LICENSE.md
License-File: AUTHORS.md
Requires-Dist: mfd-base-tool>=2.7.0
Dynamic: license-file
